azureml/__init__.py
azureml/automl/__init__.py
azureml/automl/core/LICENSE_limit_function_call
azureml/automl/core/__init__.py
azureml/automl/core/_codegen_utilities.py
azureml/automl/core/_downloader.py
azureml/automl/core/_exception_utilities.py
azureml/automl/core/_experiment_observer.py
azureml/automl/core/_shared_package_legacy_import.py
azureml/automl/core/_version.py
azureml/automl/core/automl_base_settings.py
azureml/automl/core/automl_utils.py
azureml/automl/core/config_utilities.py
azureml/automl/core/console_interface.py
azureml/automl/core/console_writer.py
azureml/automl/core/constants.py
azureml/automl/core/dataprep_utilities.py
azureml/automl/core/dataset_utilities.py
azureml/automl/core/forecasting_parameters.py
azureml/automl/core/model_explanation.py
azureml/automl/core/package_utilities.py
azureml/automl/core/py.typed
azureml/automl/core/serialization_utilities.py
azureml/automl/core/systemusage_telemetry.py
azureml/automl/core/timer_utilities.py
azureml/automl/core/utilities.py
azureml/automl/core/validated_darwin_requirements.txt
azureml/automl/core/validated_linux_requirements.txt
azureml/automl/core/validated_win32_requirements.txt
azureml/automl/core/verifier_schema.json
azureml/automl/core/_experiment_drivers/__init__.py
azureml/automl/core/_experiment_drivers/base_experiment_driver.py
azureml/automl/core/_experiment_drivers/experiment_state.py
azureml/automl/core/_logging/__init__.py
azureml/automl/core/_logging/event_logger.py
azureml/automl/core/_logging/log_server.py
azureml/automl/core/_run/__init__.py
azureml/automl/core/_run/abstract_run.py
azureml/automl/core/_run/run_lifecycle_utilities.py
azureml/automl/core/_run/types.py
azureml/automl/core/_vendor/__init__.py
azureml/automl/core/_vendor/automl/__init__.py
azureml/automl/core/_vendor/automl/client/__init__.py
azureml/automl/core/_vendor/automl/client/core/__init__.py
azureml/automl/core/configuration/__init__.py
azureml/automl/core/configuration/feature_config.py
azureml_automl_core-1.61.0.post1.dist-info/licenses/LICENSE.txt
azureml_automl_core-1.61.0.post1.dist-info/METADATA
azureml_automl_core-1.61.0.post1.dist-info/WHEEL
azureml_automl_core-1.61.0.post1.dist-info/top_level.txt
azureml_automl_core-1.61.0.post1.dist-info/RECORD
